Metadata-Version: 2.4
Name: tech-liushuai-mcp-demo
Version: 0.1.0
Summary: Add your description here
Author-email: Liu Shuai <1362809328@qq.com>
Requires-Python: >=3.13
Requires-Dist: mcp[cli]>=1.11.0
